psj_lib/__init__.py
psj_lib/_internal/_reentrant_lock.py
psj_lib/devices/ADDING_NEW_DEVICES.md
psj_lib/devices/base/__init__.py
psj_lib/devices/base/capabilities/__init__.py
psj_lib/devices/base/capabilities/actuator_description.py
psj_lib/devices/base/capabilities/capability_descriptor.py
psj_lib/devices/base/capabilities/closed_loop_controller.py
psj_lib/devices/base/capabilities/data_recorder.py
psj_lib/devices/base/capabilities/error_low_pass_filter.py
psj_lib/devices/base/capabilities/factory_reset.py
psj_lib/devices/base/capabilities/fan.py
psj_lib/devices/base/capabilities/low_pass_filter.py
psj_lib/devices/base/capabilities/modulation_source.py
psj_lib/devices/base/capabilities/monitor_output.py
psj_lib/devices/base/capabilities/notch_filter.py
psj_lib/devices/base/capabilities/pcf.py
psj_lib/devices/base/capabilities/pid_controller.py
psj_lib/devices/base/capabilities/piezo_capability.py
psj_lib/devices/base/capabilities/position.py
psj_lib/devices/base/capabilities/setpoint.py
psj_lib/devices/base/capabilities/slew_rate.py
psj_lib/devices/base/capabilities/static_waveform_generator.py
psj_lib/devices/base/capabilities/status.py
psj_lib/devices/base/capabilities/temperature.py
psj_lib/devices/base/capabilities/trigger_out.py
psj_lib/devices/base/capabilities/units.py
psj_lib/devices/base/command_cache.py
psj_lib/devices/base/device_factory.py
psj_lib/devices/base/exceptions.py
psj_lib/devices/base/piezo_channel.py
psj_lib/devices/base/piezo_device.py
psj_lib/devices/base/piezo_types.py
psj_lib/devices/d_drive_family/__init__.py
psj_lib/devices/d_drive_family/capabilities/d_drive_closed_loop_controller.py
psj_lib/devices/d_drive_family/capabilities/d_drive_data_recorder.py
psj_lib/devices/d_drive_family/capabilities/d_drive_modulation_source.py
psj_lib/devices/d_drive_family/capabilities/d_drive_monitor_output.py
psj_lib/devices/d_drive_family/capabilities/d_drive_setpoint.py
psj_lib/devices/d_drive_family/capabilities/d_drive_status_register.py
psj_lib-1.1.0.dist-info/METADATA
psj_lib-1.1.0.dist-info/WHEEL
psj_lib-1.1.0.dist-info/RECORD
