Metadata-Version: 2.4
Name: psj-lib
Version: 1.1.0
Summary: Python library for amplifiers and other devices of piezosystem jena
Author: piezosystem jena GmbH
Requires-Python: >=3.12,<4.0
Classifier: Development Status :: 5 - Production/Stable
Classifier: Intended Audience :: Developers
Classifier: Operating System :: OS Independent
Classifier: Programming Language :: Python :: 3
Classifier: Programming Language :: Python :: 3.12
Classifier: Programming Language :: Python :: 3.13
Classifier: Programming Language :: Python :: 3.14
Requires-Dist: aioserial (>=1.3.1,<2.0.0)
Requires-Dist: psutil (>=7.0.0,<8.0.0)
Requires-Dist: telnetlib3 (>=2.0.4,<3.0.0)
Project-URL: Bug Tracker, https://github.com/piezosystemjena/psj-lib/issues
Project-URL: Documentation, https://piezosystemjena.github.io/psj-lib/
Project-URL: Homepage, https://github.com/piezosystemjena/psj-lib
Project-URL: Source, https://github.com/piezosystemjena/psj-lib
